mcp_config.py
mcp_data.py
mcp_operations.py
mcp_scanner.py
mcp_tui.py
ccmanager-2.0.1.dist-info/licenses/LICENSE
ccmanager-2.0.1.dist-info/METADATA
ccmanager-2.0.1.dist-info/WHEEL
ccmanager-2.0.1.dist-info/entry_points.txt
ccmanager-2.0.1.dist-info/top_level.txt
ccmanager-2.0.1.dist-info/RECORD
