Metadata-Version: 2.4
Name: ccmanager
Version: 2.0.1
Summary: Terminal UI for managing Claude Code configurations across all your projects
Author: Simon Strumse
License-Expression: MIT
Project-URL: Homepage, https://github.com/simonstrumse/claude-code-manager
Project-URL: Repository, https://github.com/simonstrumse/claude-code-manager
Project-URL: Issues, https://github.com/simonstrumse/claude-code-manager/issues
Keywords: claude,anthropic,mcp,model-context-protocol,tui,terminal,cli
Classifier: Development Status :: 4 - Beta
Classifier: Environment :: Console
Classifier: Intended Audience :: Developers
Classifier: Operating System :: OS Independent
Classifier: Programming Language :: Python :: 3
Classifier: Programming Language :: Python :: 3.8
Classifier: Programming Language :: Python :: 3.9
Classifier: Programming Language :: Python :: 3.10
Classifier: Programming Language :: Python :: 3.11
Classifier: Programming Language :: Python :: 3.12
Classifier: Topic :: Software Development :: Libraries :: Python Modules
Classifier: Topic :: Utilities
Requires-Python: >=3.8
License-File: LICENSE
Requires-Dist: textual>=0.47.0
Requires-Dist: rich>=13.0.0
Requires-Dist: pyyaml>=6.0
Dynamic: license-file
